easy_config/__init__.py
easy_config/contrib/__init__.py
easy_config/contrib/click.py
easy_config-0.2.0.dist-info/LICENSE.txt
easy_config-0.2.0.dist-info/METADATA
easy_config-0.2.0.dist-info/RECORD
easy_config-0.2.0.dist-info/WHEEL
easy_config-0.2.0.dist-info/top_level.txt
easy_config-0.2.0.dist-info/zip-safe
