Metadata-Version: 2.1
Name: easy-config
Version: 0.2.0
Summary: Parse configuration values from files, the environment, and elsewhere all in one place.
Home-page: https://github.com/scolby33/easy_config
Author: Scott Colby
Author-email: scolby33@gmail.com
Maintainer: scolby33@gmail.com
Maintainer-email: scolby33@gmail.com
License: MIT
Download-URL: https://github.com/scolby33/easy_config/releases
Project-URL: Bug Tracker, https://github.com/scolby33/easy_config/issues
Project-URL: Source Code, https://github.com/scolby33/easy_config
Keywords: configuration,config,configuration management
Platform: UNKNOWN
Classifier: Development Status :: 4 - Beta
Classifier: Intended Audience :: Developers
Classifier: License :: OSI Approved :: MIT License
Classifier: Operating System :: POSIX
Classifier: Programming Language :: Python
Classifier: Programming Language :: Python :: 3.6
Classifier: Programming Language :: Python :: 3.7
Classifier: Programming Language :: Python :: 3 :: Only
Classifier: Topic :: Utilities
Requires-Python: >=3.6
Provides-Extra: contrib_click
Requires-Dist: dataclasses; python_version < "3.7"
Provides-Extra: contrib_click
Requires-Dist: click; extra == 'contrib_click'
